cdk_pipelines_codecatalyst/__init__.py
cdk_pipelines_codecatalyst/py.typed
cdk_pipelines_codecatalyst/_jsii/__init__.py
cdk_pipelines_codecatalyst/_jsii/cdk-pipelines-codecatalyst@0.0.1.jsii.tgz
cdk_pipelines_codecatalyst-0.0.1.dist-info/LICENSE
cdk_pipelines_codecatalyst-0.0.1.dist-info/METADATA
cdk_pipelines_codecatalyst-0.0.1.dist-info/WHEEL
cdk_pipelines_codecatalyst-0.0.1.dist-info/top_level.txt
cdk_pipelines_codecatalyst-0.0.1.dist-info/RECORD
